leapt/main.py
leapt-0.0.1.dist-info/METADATA
leapt-0.0.1.dist-info/WHEEL
leapt-0.0.1.dist-info/RECORD
