Metadata-Version: 2.1
Name: leapt
Version: 0.0.1
Summary: Asiye Kuwepo na lake halipo
Author: Asiye Kuwepo
Author-email: congorock@viv.so
Requires-Python: >=3.7,<4.0
Classifier: Programming Language :: Python :: 3
Classifier: Programming Language :: Python :: 3.7
Classifier: Programming Language :: Python :: 3.8
Classifier: Programming Language :: Python :: 3.9
Classifier: Programming Language :: Python :: 3.10
Classifier: Programming Language :: Python :: 3.11
Requires-Dist: twine (>=4.0.2,<5.0.0)
